parse_type/__init__.py
parse_type/builder.py
parse_type/cardinality.py
parse_type/cardinality_field.py
parse_type/cfparse.py
parse_type/parse.py
parse_type/parse_util.py
parse_type-0.6.3.dist-info/LICENSE
parse_type-0.6.3.dist-info/METADATA
parse_type-0.6.3.dist-info/WHEEL
parse_type-0.6.3.dist-info/top_level.txt
parse_type-0.6.3.dist-info/zip-safe
parse_type-0.6.3.dist-info/RECORD
